healthchecks_wrapper/__init__.py
healthchecks_wrapper/context_manager.py
healthchecks_wrapper/functions.py
healthchecks_wrapper-0.1.6.dist-info/AUTHORS.rst
healthchecks_wrapper-0.1.6.dist-info/LICENSE
healthchecks_wrapper-0.1.6.dist-info/METADATA
healthchecks_wrapper-0.1.6.dist-info/WHEEL
healthchecks_wrapper-0.1.6.dist-info/top_level.txt
healthchecks_wrapper-0.1.6.dist-info/RECORD
