Metadata-Version: 2.1
Name: healthchecks-wrapper
Version: 0.1.6
Summary: Context manager around service provided by HealthChecks for easy use
Home-page: https://github.com/samarpan-rai/healthchecks_wrapper
Author: Samarpan Rai
Author-email: samarpan-rai@live.com
License: MIT license
Keywords: healthchecks_context_manager
Platform: UNKNOWN
Classifier: Intended Audience :: Developers
Classifier: License :: OSI Approved :: MIT License
Classifier: Natural Language :: English
Requires-Python: >=3.6
